neatcpp/__init__.py
neatcpp/__main__.py
neatcpp/neatcpp.py
neatcpp-1.2.0.dist-info/licenses/LICENSE
neatcpp-1.2.0.dist-info/METADATA
neatcpp-1.2.0.dist-info/WHEEL
neatcpp-1.2.0.dist-info/entry_points.txt
neatcpp-1.2.0.dist-info/top_level.txt
neatcpp-1.2.0.dist-info/RECORD
