Metadata-Version: 2.4
Name: neatcpp
Version: 1.2.0
Summary: A minimalistic C preprocessor preserving the original C code formatting
Author-email: Lubomir Milko <lubomir.milko@gmail.com>
License-Expression: GPL-3.0
Project-URL: Repository, https://github.com/lubomilko/neatcpp
Project-URL: Documentation, https://github.com/lubomilko/neatcpp/blob/main/README.md
Project-URL: Issues, https://github.com/lubomilko/neatcpp/issues
Classifier: Programming Language :: Python :: 3
Classifier: Operating System :: OS Independent
Classifier: Intended Audience :: Developers
Requires-Python: >=3.10
License-File: LICENSE
Dynamic: license-file
